torrent_search/__init__.py
torrent_search/__main__.py
torrent_search/fastapi_server.py
torrent_search/mcp_server.py
torrent_search/test_mcp_server.py
torrent_search/wrapper/__init__.py
torrent_search/wrapper/api_client.py
torrent_search/wrapper/models.py
torrent_search/wrapper/scraper.py
torrent_search/wrapper/utils.py
torrent_search_mcp-2.0.3.dist-info/METADATA
torrent_search_mcp-2.0.3.dist-info/WHEEL
torrent_search_mcp-2.0.3.dist-info/entry_points.txt
torrent_search_mcp-2.0.3.dist-info/licenses/LICENSE
torrent_search_mcp-2.0.3.dist-info/RECORD
