Metadata-Version: 2.4
Name: torrent-search-mcp
Version: 2.0.3
Summary: Torrent Search MCP Server
Project-URL: Repository, https://github.com/philogicae/torrent-search-mcp
Project-URL: Release, https://github.com/philogicae/torrent-search-mcp/releases
Project-URL: DeepWiki, https://deepwiki.com/philogicae/torrent-search-mcp
Author: philogicae
License-Expression: MIT
License-File: LICENSE
Requires-Python: <4.0,>=3.10
Requires-Dist: aiocache
Requires-Dist: crawl4ai
Requires-Dist: fastapi
Requires-Dist: fastmcp
Requires-Dist: fr-torrent-search-mcp
Requires-Dist: pybase62
